README.rst
setup.py
PyPeopleNames/PyPeopleNames.py
PyPeopleNames/__init__.py
PyPeopleNames.egg-info/PKG-INFO
PyPeopleNames.egg-info/SOURCES.txt
PyPeopleNames.egg-info/dependency_links.txt
PyPeopleNames.egg-info/top_level.txt