Metadata-Version: 1.0
Name: PyPeopleNames
Version: 1.0
Summary:  A python package to extract full western 'people' names from a string
Home-page: https://github.com/nogoodconfig/pypeoplenames
Author: nogoodconfig
Author-email: UNKNOWN
License:  MIT License
Platform: UNKNOWN
